{"chunk_definitions":[{"row":30,"row_count":1,"visible":true,"expansion_state":0,"options":{"engine":"r","label":"fig-modeling-splines-parabola","echo":false,"fig.cap":"Illustration of a parabolic relationship between a response and a predictor.","fig.alt":null,"dev":"png"},"document_id":"5D50E03F","chunk_id":"cv3d1uhfasqu9","chunk_label":"fig-modeling-splines-parabola"},{"row":107,"row_count":1,"visible":true,"expansion_state":0,"options":{"engine":"r","label":"fig-modeling-splines-linear-spline","echo":false,"fig.cap":"Illustration of a linear spline with two know points.","fig.alt":"Scatterplot with best-fit line overlaid that changes direction two times.","dev":"png"},"document_id":"5D50E03F","chunk_id":"c2su24deu37nz","chunk_label":"fig-modeling-splines-linear-spline"},{"row":224,"row_count":1,"visible":true,"expansion_state":0,"options":{"engine":"r","label":"fig-modeling-splines-rcs","echo":false,"fig.cap":"Illustration of a restricted cubic spline with five knot points.","fig.alt":"Curved line captured created by spline.","dev":"png"},"document_id":"5D50E03F","chunk_id":"ca9sho14g9mtm","chunk_label":"fig-modeling-splines-rcs"}],"doc_write_time":1709242632}